feiticeiro_tec/__init__.py
feiticeiro_tec/config/__init__.py
feiticeiro_tec/config/with_dynaconf.py
feiticeiro_tec/flask/__init__.py
feiticeiro_tec/flask/compress.py
feiticeiro_tec/flask/job_manager/__init__.py
feiticeiro_tec/flask/job_manager/jobs.py
feiticeiro_tec/flask/job_manager/templates/job_manager/_component_job_macro.html
feiticeiro_tec/flask/job_manager/templates/job_manager/_component_job_style.html
feiticeiro_tec/flask/job_manager/templates/job_manager/index.html
feiticeiro_tec/flask/job_manager/templates/job_manager/reload.html
feiticeiro_tec/flask/rule_router/__init__.py
feiticeiro_tec/pydantic/contato.py
feiticeiro_tec/pydantic/credencial.py
feiticeiro_tec/pydantic/empresa.py
feiticeiro_tec/pydantic/endereco.py
feiticeiro_tec/request/__init__.py
feiticeiro_tec/request/cep.py
feiticeiro_tec/validate/__init__.py
feiticeiro_tec/validate/abs.py
feiticeiro_tec/validate/types.py
feiticeiro_tec/validate/validates.py
feiticeiro_tec-0.4.0.dist-info/METADATA
feiticeiro_tec-0.4.0.dist-info/WHEEL
feiticeiro_tec-0.4.0.dist-info/top_level.txt
feiticeiro_tec-0.4.0.dist-info/RECORD
