Metadata-Version: 2.1
Name: feiticeiro_tec
Version: 0.4.0
Summary: pacote de utilidades para projetos python
Home-page: https://github.com/feiticeiro-tec/feiticeiro-tec
Author: Silvio Henrique Cruz Da Silva
Author-email: silviohenriquecruzdasilva@gmail.com
License: BSD3
Keywords: python,feiticeiro_tec,utilidades,feiticeiro,tec
Requires-Dist: loguru
Requires-Dist: pydantic
Provides-Extra: dynaconf
Requires-Dist: dynaconf ; extra == 'dynaconf'
Provides-Extra: flask
Requires-Dist: flask ; extra == 'flask'
Requires-Dist: flask-admin ; extra == 'flask'
Requires-Dist: flask-sqlalchemy ; extra == 'flask'
Provides-Extra: request
Requires-Dist: requests ; extra == 'request'
Provides-Extra: validate
Requires-Dist: validate-docbr ; extra == 'validate'
